emojislib/__cli__.py
emojislib/__init__.py
emojislib/__main__.py
emojislib/__version__.py
emojislib/emojis.py
emojislib-0.0.1.dist-info/LICENSE
emojislib-0.0.1.dist-info/METADATA
emojislib-0.0.1.dist-info/WHEEL
emojislib-0.0.1.dist-info/entry_points.txt
emojislib-0.0.1.dist-info/top_level.txt
emojislib-0.0.1.dist-info/RECORD
